sippy_unipi/OLSims_methods.py
sippy_unipi/Parsim_methods.py
sippy_unipi/__init__.py
sippy_unipi/armax.py
sippy_unipi/arx.py
sippy_unipi/functionset.py
sippy_unipi/functionsetSIM.py
sippy_unipi/functionset_OPT.py
sippy_unipi/io_opt.py
sippy_unipi/io_rls.py
sippy_unipi/model.py
sippy_unipi/typing.py
sippy_unipi/utils.py
sippy_unipi-1.0.2.dist-info/LICENSE
sippy_unipi-1.0.2.dist-info/METADATA
sippy_unipi-1.0.2.dist-info/WHEEL
sippy_unipi-1.0.2.dist-info/RECORD
