Metadata-Version: 2.3
Name: sippy_unipi
Version: 1.0.2
Summary: Systems Identification Package for Python
License: LGPL-3.0-or-later
Keywords: system identification,control systems,ARMAX,ARX,state-space
Author: Giuseppe Armenise
Requires-Python: >=3.10
Classifier: Development Status :: 4 - Beta
Classifier: Intended Audience :: Education
Classifier: Intended Audience :: Science/Research
Classifier: License :: OSI Approved :: GNU Lesser General Public License v3 (LGPLv3)
Classifier: Programming Language :: Python :: 3
Requires-Dist: casadi (<4.0.0)
Requires-Dist: control (<1.0.0)
Requires-Dist: numpy (<3.0.0)
Requires-Dist: scipy (<2.0.0)
Requires-Dist: slycot (<1.0.0)
Project-URL: Repository, https://github.com/CPCLAB-UNIPI/sippy
